duke/__init__.py
duke/common.py
duke/conf.py
duke/get_plugins.py
duke/utils.py
django_duke-0.1.0.dist-info/METADATA
django_duke-0.1.0.dist-info/WHEEL
django_duke-0.1.0.dist-info/RECORD
