Metadata-Version: 2.1
Name: django-duke
Version: 0.1.0
Summary: 
Author: Arkadiusz Adamski
Author-email: arkadiusz.adamski@gmail.com
Requires-Python: >=3.11,<4.0
Classifier: Programming Language :: Python :: 3
Classifier: Programming Language :: Python :: 3.11
Classifier: Programming Language :: Python :: 3.12
Requires-Dist: django (>=3.2.9,<6.0.0)
